oopycql/__init__.py
oopycql/cypher.py
oopycql/errors.py
oopycql/oopycql_collections.py
oopycql/query.py
oopycql-1.1.5a2.dist-info/LICENSE
oopycql-1.1.5a2.dist-info/METADATA
oopycql-1.1.5a2.dist-info/WHEEL
oopycql-1.1.5a2.dist-info/top_level.txt
oopycql-1.1.5a2.dist-info/RECORD
