Metadata-Version: 2.1
Name: oopycql
Version: 1.1.5a2
Summary: An object oritneted interface for the cypher query language
Home-page: https://github.com/DomWeldon/oopycql
Author: Dom Weldon
Author-email: dom.weldon@gmail.com
License: Apache License, Version 2.0
Download-URL: https://github.com/domweldon/oopycql/archive/1.1.5a2.tar.gz
Keywords: graph database neo4j cypher cql
Platform: any
Classifier: Development Status :: 3 - Alpha
Classifier: Environment :: Web Environment
Classifier: Intended Audience :: Developers
Classifier: Operating System :: OS Independent
Classifier: Programming Language :: Python
Classifier: Topic :: Internet :: WWW/HTTP :: Dynamic Content
Classifier: Topic :: Software Development :: Libraries :: Python Modules
Classifier: Programming Language :: Python :: 2.7
Classifier: Programming Language :: Python :: 3.3
Classifier: Programming Language :: Python :: 3.4
Classifier: Programming Language :: Python :: 3.5
Classifier: Programming Language :: Python :: 3.6
Classifier: Topic :: Database
Requires-Python: >=2.7
Requires-Dist: six
Requires-Dist: regex
